Metadata-Version: 1.1
Name: dash-tour-component
Version: 0.0.2
Summary: Tour component for Dash (made by plotly) to give your dash app a tour
Home-page: https://github.com/matthijsramlab/dash_tour_component
Author: Matthijs Visser <vldmatthijs@gmail.com>
Author-email: UNKNOWN
License: MIT
Platform: UNKNOWN
Classifier: Framework :: Dash
